yolov4/__init__.py
yolov4/common/__init__.py
yolov4/common/base_class.py
yolov4/common/media.py
yolov4/common/predict.py
yolov4/model/__init__.py
yolov4/model/backbone.py
yolov4/model/common.py
yolov4/model/head.py
yolov4/model/neck.py
yolov4/model/yolov4.py
yolov4/tf/__init__.py
yolov4/tf/dataset.py
yolov4/tf/train.py
yolov4/tf/weights.py
yolov4/tflite/__init__.py
yolov4/weights/__init__.py
yolov4/weights/classes.names
yolov4/weights/yolov4-tiny-final.weights
customyolov4-2.dist-info/METADATA
customyolov4-2.dist-info/WHEEL
customyolov4-2.dist-info/top_level.txt
customyolov4-2.dist-info/RECORD
